<annotation>
	<folder>collectedimagesv3</folder>
	<filename>Thumbs_up.84475bb4-76af-11eb-84d2-f8ac65edf6e7.jpg</filename>
	<path>E:\RealTimeHandGestureRecognition\Tensorflow\workspace\images\collectedimagesv3\Thumbs_up.84475bb4-76af-11eb-84d2-f8ac65edf6e7.jpg</path>
	<source>
		<database>Unknown</database>
	</source>
	<size>
		<width>640</width>
		<height>480</height>
		<depth>3</depth>
	</size>
	<segmented>0</segmented>
	<object>
		<name>Thumbs up</name>
		<pose>Unspecified</pose>
		<truncated>0</truncated>
		<difficult>0</difficult>
		<bndbox>
			<xmin>157</xmin>
			<ymin>220</ymin>
			<xmax>234</xmax>
			<ymax>364</ymax>
		</bndbox>
	</object>
</annotation>
